api_orm/__init__.py
api_orm/core/__init__.py
api_orm/core/condition.py
api_orm/core/exception.py
api_orm/core/field.py
api_orm/core/model.py
api_orm/core/query.py
api_orm/core/session.py
provider/__init__.py
provider/hs/__init__.py
provider/hs/client.py
provider/hs/exceptions.py
provider/hs/helpers.py
provider/hs/mapping/__init__.py
provider/hs/mapping/field_mapper.py
provider/hs/mapping/field_mapping.json
provider/hs/models.py
provider/hs/session.py
py_api_orm-0.1.0.dist-info/METADATA
py_api_orm-0.1.0.dist-info/WHEEL
py_api_orm-0.1.0.dist-info/RECORD
