Metadata-Version: 2.4
Name: py-api-orm
Version: 0.1.0
Summary: ORM like SDK to interact with APIs
Author: Fabian Dill
Author-email: fabian.dill@lumanaa.de
Requires-Python: >=3.13
Classifier: Programming Language :: Python :: 3
Classifier: Programming Language :: Python :: 3.13
Classifier: Programming Language :: Python :: 3.14
Requires-Dist: hubspot-api-client (>=12.0.0,<13.0.0)
Requires-Dist: pydantic[email] (>=2.11.7,<3.0.0)
Requires-Dist: python-dotenv (>=1.0.1,<2.0.0)
